LICENSE
MANIFEST.in
README.md
setup.py
pull_dash_components/AppInput.py
pull_dash_components/FullscreenPanel.py
pull_dash_components/Input.py
pull_dash_components/Panel.py
pull_dash_components/PullDashComponents.py
pull_dash_components/__init__.py
pull_dash_components/_imports_.py
pull_dash_components/index.py
pull_dash_components/metadata.json
pull_dash_components/package-info.json
pull_dash_components/package.json
pull_dash_components/pull_dash_components.js
pull_dash_components.egg-info/PKG-INFO
pull_dash_components.egg-info/SOURCES.txt
pull_dash_components.egg-info/dependency_links.txt
pull_dash_components.egg-info/top_level.txt