Metadata-Version: 2.1
Name: pull-dash-components
Version: 1.0.1
Summary: Dash UI component for pull dashboards
Home-page: UNKNOWN
Author: pull systems <engineering@pull.systems>
License: MIT
Platform: UNKNOWN
Classifier: Framework :: Dash
License-File: LICENSE
